<author lang="en">
	<documents>
		<document><![CDATA[I was forced to have an EXORCISM because a priest was so scared of my demonic tattoos #URL#]]></document>
		<document><![CDATA[Moon hopes for free trade deal with Mexico #URL#]]></document>
		<document><![CDATA[Dog owners issued urgent warning to clean up after their pets as farmer loses half of cows over contaminated grass #URL#]]></document>
		<document><![CDATA[Reddit Users Explode Over Kim Kardashian’s Latest Skims Release #URL#]]></document>
		<document><![CDATA[(Yonhap Feature) As pandemic wipes out gatherings, alcohol industry sets eyes on at-home drinkers #URL#]]></document>
		<document><![CDATA[‘We’re next’: Prisoner’s secret filming appears to show torture in Cairo police station #URL#]]></document>
		<document><![CDATA[ET Online Survey: Top talking points ahead of another pandemic Budget #URL#]]></document>
		<document><![CDATA[Jamaica vs. Mexico: Time, TV channel, stream, lineups, betting odds for soccer World Cup qualifier #URL#]]></document>
		<document><![CDATA[Teen Moms Briana DeJesus and Jade Cline accused of ‘mocking LGBTQ community’ as they joke about dating each other #URL#]]></document>
		<document><![CDATA[Kyle Rittenhouse gun from Kenosha shootings to be destroyed #URL#]]></document>
		<document><![CDATA[I tried to EAT myself to death as one of UK’s fattest men – I’d have 6 cheese toasties for breakfast but look at me now #URL#]]></document>
		<document><![CDATA[BBC boss takes swipe at Nadine Dorries over BBC funding #URL#]]></document>
		<document><![CDATA[Pittsburgh bridge collapses hours before Biden tour on infrastructure #URL#]]></document>
		<document><![CDATA[Is Nuggets’ Nikola Jokic carving a clear path towards another MVP award? #URL#]]></document>
		<document><![CDATA[Teen Mom’s Amber Portwood admits she ‘hasn’t seen’ daughter Leah, 12, in ‘quite some time &amp; it’s not right’ #URL#]]></document>
		<document><![CDATA[Former Miss America shares Ring cam of self-proclaimed white nationalists trying to recruit in Alabama #URL#]]></document>
		<document><![CDATA[Best laptop deals in the UK for January 2022: We’ve found discounts on big-name brands #URL#]]></document>
		<document><![CDATA[Ukraine-Russia explained: A simple guide to what’s going on #URL#]]></document>
		<document><![CDATA[Lee vows to push for 4 1/2-day workweek #URL#]]></document>
		<document><![CDATA[Teenager in court over ‘hate crime’ after two men attacked in north London #URL#]]></document>
		<document><![CDATA[(URGENT) S. Korea voices ‘strong regret’ over Japan’s decision to recommend Sado mine for World Heritage designation #URL#]]></document>
		<document><![CDATA[How Babes in the Wood killer escaped justice for 30 years after double child murder – and only served 4 in jail #URL#]]></document>
		<document><![CDATA[Boris Johnson news – live: Redacted Sue Gray report ‘imminent’ as Met Police denies delaying publication #URL#]]></document>
		<document><![CDATA[French parliament backs law banning conversion therapies #URL#]]></document>
		<document><![CDATA[Australian Open LIVE: Iga Swiatek vs Danielle Collins tennis updates after Ash Barty defeats Madison Keys #URL#]]></document>
		<document><![CDATA[Hyosung Q4 net income up 97.6 pct to 90 bln won #URL#]]></document>
		<document><![CDATA[China demands US halt Olympics ‘interference’ #URL#]]></document>
		<document><![CDATA[Teen Mom’s pregnant Catelynn Lowell takes midnight soak in bathtub as she struggles to sleep at 37 weeks along #URL#]]></document>
		<document><![CDATA[Teen Mom’s Kailyn Lowry takes a swipe at her ex Chris Lopez saying he ‘forgets to show up’ for the kids in new clip #URL#]]></document>
		<document><![CDATA[Ocado’s court battle with AutoStore in Germany put on hold #URL#]]></document>
		<document><![CDATA[Bruno Guimaraes set for Newcastle medical while in South America on international duty ahead of £43m move #URL#]]></document>
		<document><![CDATA[Teen Mom’s Amber Portwood Details Strained Relationship With Daughter Leah #URL#]]></document>
		<document><![CDATA[My house is so mouldy I have to sleep on my living room sofa – I’m too embarrassed to have friends over #URL#]]></document>
		<document><![CDATA[The Love Island boss “wants to have an application from non-binary people” #URL#]]></document>
		<document><![CDATA[Rivaldo, Hazard and Dybala in Tottenham’s best XI of fluffed transfers with Luis Diaz set to join star-studded team #URL#]]></document>
		<document><![CDATA[Reddit Users Find Answers to 10 Tricky Questions That Could Keep Us Awake the Whole Night #URL#]]></document>
		<document><![CDATA[British judges have no place in Hong Kong #URL#]]></document>
		<document><![CDATA[Rams vs. Buccaneers final score, results: Matt Gay walk-off field goal advances Rams to NFC Championship #URL#]]></document>
		<document><![CDATA[Reigning Olympic skeleton champion not considering self as medal contender in Beijing #URL#]]></document>
		<document><![CDATA[Josh Allen may have jinxed Bills’ AFC championship game hopes in sideline video #URL#]]></document>
		<document><![CDATA[Moment cruel driver dumps seven dogs – leaving them ‘confused &amp; distressed’ as RSPCA braces for surge in abandoned pets #URL#]]></document>
		<document><![CDATA[Ben Roethlisberger retires: NFL reacts to news Steelers QB is calling it quits #URL#]]></document>
		<document><![CDATA[I didn’t know my date was living a double life until his wife called me – he hid her stuff before I went to THEIR house #URL#]]></document>
		<document><![CDATA[‘A weird accident’: Police say death of teen found in rolled-up school gym mat was not a crime #URL#]]></document>
		<document><![CDATA[(URGENT) Samsung Electronics Q4 sales up 24.4 pct on-year to 76.5 tln won #URL#]]></document>
		<document><![CDATA[Voices: Donald Trump Jr is making jokes about Hunter Biden and SCOTUS because he knows he’s already won #URL#]]></document>
		<document><![CDATA[Sue Gray news – live: Boris Johnson faces PMQs grilling as No 10 kept waiting on lockdown parties report #URL#]]></document>
		<document><![CDATA[Rejected by New Zealand, reporter turns to Taliban for help #URL#]]></document>
		<document><![CDATA[Mali vs Equatorial Guinea LIVE: Stream, score, TV channel, kick-off time and team news – AFCON latest updates #URL#]]></document>
		<document><![CDATA[I’m a psychologist – here’s the one thing you must ask the person you’re dating about their ex-partners #URL#]]></document>
		<document><![CDATA[We went on a Love Holidays ski trip and ended up ‘refugees’ as slopes closed after ONE HOUR – we want our £2,000 back #URL#]]></document>
		<document><![CDATA[Fish growth slowed by high temperatures and plastic chemical BPA, research shows #URL#]]></document>
		<document><![CDATA[Collapsed Pittsburgh bridge is one of 44,000 in poor condition in US #URL#]]></document>
		<document><![CDATA[This Founder Wants Machine Learning Developers to Change the World #URL#]]></document>
		<document><![CDATA[Covid live: two-thirds of people with Omicron in England had Covid before; Netherlands to reopen bars and cafes #URL#]]></document>
		<document><![CDATA[Sue Gray report should be released NOW say MPs #URL#]]></document>
		<document><![CDATA[Teen Mom’s Catelynn Lowell says she’s ‘so done’ with pregnancy at 37 weeks as she awaits fourth child’s arrival #URL#]]></document>
		<document><![CDATA[Man shares tour of 100-square-foot apartment and his tips for utilising small spaces #URL#]]></document>
		<document><![CDATA[I’m an expert – my simple trick will stop your car from smelling and you won’t have to do a single second of cleaning #URL#]]></document>
		<document><![CDATA[Insider Shares Where Rams’ Sean McVay is at His Strongest #URL#]]></document>
		<document><![CDATA[Steelers Star Defensive End Puts Pittsburgh Home Up For Sale #URL#]]></document>
		<document><![CDATA[Chiefs could use Tyreek Hill at punt returner again in AFC championship game #URL#]]></document>
		<document><![CDATA[Graduates in England face ‘tax rise by stealth’ on student loans #URL#]]></document>
		<document><![CDATA[Highway Code changes – New major rules come into force TOMORROW; what drivers, cyclists &amp; pedestrians need to know #URL#]]></document>
		<document><![CDATA[‘If she has a problem, she comes to me’: the retired care worker helping to fight local loneliness #URL#]]></document>
		<document><![CDATA[Teen Mom’s Kailyn and Ex Javi Spark Reconciliation Rumors: What We Know #URL#]]></document>
		<document><![CDATA[Virginia Giuffre’s team blast Prince Andrew for ‘victim blaming’ and vow to expose him in court #URL#]]></document>
		<document><![CDATA[Japan in final consultations to recommend Sado mine as UNESCO heritage site: report #URL#]]></document>
		<document><![CDATA[Fibbing is part of Boris Johnson’s toolkit but could be his undoing #URL#]]></document>
		<document><![CDATA[Inside the luxury life of Gunther IV – a pampered German shepherd who inherited a £280million fortune #URL#]]></document>
		<document><![CDATA[Curt Schilling Congratulates David Ortiz On Twitter, Before Ranting About BBWAA During A Live Stream #URL#]]></document>
		<document><![CDATA[Creating a financially-flexible business gives you confidence that you’ll be able to pivot as markets change. #USER# #URL#]]></document>
		<document><![CDATA[Teen Mom’s Javi Marroquin praised as ‘the best dad’ after sharing video of son Lincoln, 8, crying over Christmas gift #URL#]]></document>
		<document><![CDATA[Michael Rapaport films shoplifter walk out of Rite Aid and blames ex-mayor of New York #URL#]]></document>
		<document><![CDATA[UK arms exports delayed ‘for up to six months’ due to Brexit #URL#]]></document>
		<document><![CDATA[The Speed Bump sex position promises seriously intense orgasms &amp; it’s ideal for lazy girls #URL#]]></document>
		<document><![CDATA[Avenatti trial – live: Stormy Daniels talks Trump in Cohen interview as ex-lawyer aims to cross-examine her #URL#]]></document>
		<document><![CDATA[Teen Moms’ most elaborate holiday decorations featuring Maci Bookout’s two-story tree #URL#]]></document>
		<document><![CDATA[Prince Harry &amp; Meghan Markle ‘asked for secret talks’ with Spiderman couple Tom Holland &amp; Zendaya despite never meeting #URL#]]></document>
		<document><![CDATA[Judge denies media ban ahead of cop’s trial over Taylor raid #URL#]]></document>
		<document><![CDATA[How the West is squaring up to Putin’s war machine with ‘thousands of troops’, javelin missiles &amp; F-16 fighter jets #URL#]]></document>
		<document><![CDATA[Teen Mom’s Bristol Palin spoils son Tripp with $210 Gucci slides in belated 13th birthday present #URL#]]></document>
		<document><![CDATA[(LEAD) S. Korea hits grim COVID-19 milestone of over 13,000 daily cases as omicron fears worsen #URL#]]></document>
		<document><![CDATA[Florida Girl, 12, Tries to Hang herself in School’s Bathroom After ‘Gender Identity Issues’ led to Bullying #URL#]]></document>
		<document><![CDATA[Lauren Malt: Dad, 44, appears in court after ‘murdering daughter, 19, in crash’ #URL#]]></document>
		<document><![CDATA[S. Korea activates task force for emergency economic responses over Ukraine tension #URL#]]></document>
		<document><![CDATA[Investment in adult literacy could play a major role in ‘levelling up’ | Letters #URL#]]></document>
		<document><![CDATA[I face £460 fines &amp; my car was towed after parking signs were painted over – I refuse to pay #URL#]]></document>
		<document><![CDATA[Draft Analyst Puts Lions Rookies on Significant List After Season #URL#]]></document>
		<document><![CDATA[Ottawa police get reinforcements as anti-vax convoy arrives #URL#]]></document>
		<document><![CDATA[Arsenal face major dilemma and fear they will make NO January transfers despite having just 20 active players in squad #URL#]]></document>
		<document><![CDATA[Teen Mom’s Bar Smith wears sweater &amp; gold chain after starting laser treatment to remove face tattoos in major makeover #URL#]]></document>
		<document><![CDATA[Halle Berry says she posted fake Van Hunt marriage photos after ‘copious amounts of drinks’ #URL#]]></document>
		<document><![CDATA[The number of serving cops in YOUR area who are convicted criminals revealed as police hire thieves #URL#]]></document>
		<document><![CDATA[Bengals QB Joe Burrow expecting Chiefs’ Arrowhead Stadium to be ‘really loud’ #URL#]]></document>
		<document><![CDATA[‘Take It Very Seriously’: Gov. Baker Urges Mass. Residents To Stay Off Roads During Nor’easter #URL#]]></document>
		<document><![CDATA[S. Korea coach happy with players’ ‘performance and attitude’ in World Cup qualifying win #URL#]]></document>
		<document><![CDATA[Wayne Stenehjem dead at 68 – North Dakota attorney general passes away ‘unexpectedly’ as ‘kind’ lawmaker is mourned #URL#]]></document>
		<document><![CDATA[Clubhouse: Police arrest 18-year-old for creating chatroom to abuse Muslim women #URL#]]></document>
		<document><![CDATA[Samantha Schwartz, Accused Of Hiding South Shore Plaza Shooting Suspect, Arraigned #URL#]]></document>
		<document><![CDATA[Mysterious YouTube channel featuring masked man and ‘dead body’ shocks Reddit users #URL#]]></document>
		<document><![CDATA[Two Pfizer or Moderna vaccines HALVE the risk of getting ‘long Covid’, official UK data shows #URL#]]></document>
		<document><![CDATA[Lakers Sign Forward, Former Top-10 Pick to Multi-Year Contract: Report #URL#]]></document>
		<document><![CDATA[Meet the man who won a trip to space and gave it to a friend #URL#]]></document>
		<document><![CDATA[You’re painting your rooms all wrong – experts reveal the right way to do it to make things MUCH quicker #URL#]]></document>
		<document><![CDATA[Spotify removes Neil Young’s music following his Joe Rogan ultimatum #URL#]]></document>
		<document><![CDATA[Girls’ private schools could strike for the first time over pensions #URL#]]></document>
		<document><![CDATA[Analyst Explains Lions’ Dilemma Regarding Major Wideout Addition #URL#]]></document>
		<document><![CDATA[U.S. equally focused on N. Korea as all other threats: Pentagon spokesman #URL#]]></document>
		<document><![CDATA[Boston Nurse Quits Job To Earn Millions as OnlyFans Stripper, Sharing Videos of ‘Having Sex With Husband’ Online #URL#]]></document>
		<document><![CDATA[Fed to signal rate hike as it launches risky inflation fight #URL#]]></document>
		<document><![CDATA[Edward VIII letter on how he helped George VI have affair is unearthed 103 years on #URL#]]></document>
		<document><![CDATA[Covid news live: England drops all ‘plan B’ restrictions; Moderna begins trial of Omicron-specific booster shot #URL#]]></document>
		<document><![CDATA[Playoff FanDuel Picks: NFL DFS lineup advice for Bengals-Chiefs AFC Championship single-game tournaments #URL#]]></document>
		<document><![CDATA[Teen Mom’s Ryan Edwards claims he hasn’t seen son Bentley, 12, in a month &amp; ex Maci Bookout ‘POISONED’ tween against him #URL#]]></document>
		<document><![CDATA[Sexism row over backlash at Pelosi running again: ‘The same people tell Bernie to run for president’ #URL#]]></document>
		<document><![CDATA[Bodo/Glimt boss Kjetil Knutsen opens up on Celtic Euro tie fears as he lifts lid on Rangers manager link #URL#]]></document>
		<document><![CDATA[Paul Pelosi Jr. Nancy Pelosi’s Son Embroiled in 6th FBI Probe for Bribing San Francisco Official to Remove Permit Violations #URL#]]></document>
		<document><![CDATA[Government backs bill to make British Sign Language a recognised language #URL#]]></document>
		<document><![CDATA[Teen Mom’s Jenelle Evans slammed for showing ‘favoritism’ among kids as she showers Ensley with gifts as Kaiser watches #URL#]]></document>
		<document><![CDATA[Teen Mom’s Devoin Austin spends Christmas with daughter Nova, 9, &amp; ex Briana DeJesus’ child Stella, 4, in matching PJ’s #URL#]]></document>
		<document><![CDATA[Dramatic images and video show Navy stealth fighter jet crashing into ocean #URL#]]></document>
		<document><![CDATA[Ben Roethlisberger retires: Steelers QB announces end of 18-year NFL career #URL#]]></document>
		<document><![CDATA[Landon Eastep: Friend questions why police fired so many times in interstate shooting dubbed ‘suicide by cop’ #URL#]]></document>
		<document><![CDATA[England are ‘pumped’ ahead of crucial Ashes Test, Heather Knight says #URL#]]></document>
		<document><![CDATA[I asked for a delicate moon tattoo – the artist messed it up so badly, people say it looks like a burnt cookie #URL#]]></document>
		<document><![CDATA[Brooklyn Man in Traditional Jewish Dress Randomly Attacked while Walking on Street #URL#]]></document>
		<document><![CDATA[I asked for a simple heart tattoo on my arm… the artist messed it up so badly it looks like it was done with a Sharpie #URL#]]></document>
		<document><![CDATA[eFeed start-up plans to establish nutrition advisory centres across north-eastern districts #URL#]]></document>
		<document><![CDATA[One in five UK councils have no climate action plan, campaigners say #URL#]]></document>
		<document><![CDATA[Court grants Ahn’s request to stop TV debate between Lee, Yoon #URL#]]></document>
		<document><![CDATA[Holocaust Memorial Day 2022: What time is the Light a Candle event tonight? #URL#]]></document>
		<document><![CDATA[New song by The Long Blondes features in Kate Jackson art installation #URL#]]></document>
		<document><![CDATA[California Woman with MS Dies of COVID After Being Denied the Vaccine 7 Times #URL#]]></document>
		<document><![CDATA[Voices: The Conservative party does nothing to represent Muslim interests #URL#]]></document>
		<document><![CDATA[Bank mortgage rates hit highest in 7 1/2 years in December #URL#]]></document>
		<document><![CDATA[(LEAD) Samsung Biologics to acquire Biogen’s entire stake in Samsung Bioepis for US$2.3 bln #URL#]]></document>
		<document><![CDATA[Teen Mom’s Mackenzie Edwards claims Maci Bookout ‘uses her own kids to make a buck’ on TV &amp; vows NEVER to return to show #URL#]]></document>
		<document><![CDATA[‘The Boys’ Showrunner Eric Kripke Addressed Whether ‘Diabolical’ Will Be A Bingeable Show (And If It’s Canon) #URL#]]></document>
		<document><![CDATA[(URGENT) Supreme Court confirms 4-yr prison sentence for wife of ex-Justice Minister Cho Kuk #URL#]]></document>
		<document><![CDATA[What is hard Mountain Dew and when will it be available to buy? #URL#]]></document>
		<document><![CDATA[Fight Club author responds to China’s amended version: ‘Everyone gets a happy ending in China!’ #URL#]]></document>
		<document><![CDATA[Samsung logs record sales, 4-year-high operating profit in Q4 on solid chip biz #URL#]]></document>
		<document><![CDATA[Ukraine news – live: US says Russia could invade next month as UK warns of cyber-warfare #URL#]]></document>
		<document><![CDATA[Chiefs Fan’s Viral Reaction Grabs Attention of Beer Company #URL#]]></document>
		<document><![CDATA[Hunt for sex attacker targeting teenage girls #URL#]]></document>
		<document><![CDATA[Sixers’ Joel Embiid Throws Money at Pelicans Player After Technical #URL#]]></document>
		<document><![CDATA[British man, 70, dies inside ‘happy ending’ massage parlour’ in Thai ‘Sin City’ of Pattaya #URL#]]></document>
		<document><![CDATA[When is the Australian Open women’s final and how can I watch it in the UK? #URL#]]></document>
		<document><![CDATA[Teen Moms Briana DeJesus, Kayla Sessler and more stars from all franchises to film ‘crossover show for ratings boost’ #URL#]]></document>
		<document><![CDATA[Teen Mom’s Cory Wharton shows off his huge muscles after a brutal workout in new video #URL#]]></document>
		<document><![CDATA[Chiefs Fans Create Viral Tribute to Bills QB Josh Allen #URL#]]></document>
		<document><![CDATA[Nowzad founder believes Boris Johnson did not intervene in animal evacuation #URL#]]></document>
		<document><![CDATA[New poll shows Biden underwater with Wisconsin voters but still beating Trump in an election rematch #URL#]]></document>
		<document><![CDATA[Teen Mom’s Maci Bookout Reveals Where She Stands With Ryan Edwards’ Family After Reunion Drama #URL#]]></document>
		<document><![CDATA[Finley: GOP must shed its loose cannon #URL#]]></document>
		<document><![CDATA[Zane Smith Lands New Partner for Front Row Motorsports #URL#]]></document>
		<document><![CDATA[PM ‘wobbling’ on tax hike plans as No 10 awaits Sue Gray report #URL#]]></document>
		<document><![CDATA[XRP Moves With the Market as Ripple Announces Buyout #URL#]]></document>
		<document><![CDATA[‘People want to put Covid behind them’: UK pubs hopeful as drinkers return #URL#]]></document>
		<document><![CDATA[Teen Mom’s Kailyn Lowry apologizes to Demi Lovato after using their wrong pronouns and said she ‘wants to do better’ #URL#]]></document>
		<document><![CDATA[Liverpool transfer news LIVE: £14m Brazilian targeted, Sadio Mane gets concussion then scores, Tielemans race LATEST #URL#]]></document>
		<document><![CDATA[Bills GM Gives Answer on Cole Beasley’s Future With the Team #URL#]]></document>
		<document><![CDATA[Alicia Silverstone gives body-shaming photo the middle finger: ‘I think I look good’ #URL#]]></document>
		<document><![CDATA[SK Ie Technology swings to red in Q4 #URL#]]></document>
		<document><![CDATA[Teen Mom’s Catelynn Lowell Gives Birth, Welcomes Baby Girl With Tyler Baltierra #URL#]]></document>
		<document><![CDATA[Six Nations expectations soaring in Scotland despite scepticism from outside #URL#]]></document>
		<document><![CDATA[Arsenal transfer news LIVE: Arthur Melo £40m loan-to-buy, Leno to Newcastle, Osimhen £60m Aubameyang replacement #URL#]]></document>
		<document><![CDATA[Chris Whitty’s attacker Jonathan Chew faces jail after admitting to harassing health boss &amp; grabbing him in the street #URL#]]></document>
		<document><![CDATA[Bitcoin and Ethereum Try to Recover, ENJ and SAND Rally #URL#]]></document>
		<document><![CDATA[Teen Mom’s Lauren Comeau shares hug with son Eli, 2, in rare clip after she was accused of ‘hitting’ ex Javi Marroquin #URL#]]></document>
		<document><![CDATA[S. Korea beat Myanmar for 2nd straight win at Women’s Asian Cup #URL#]]></document>
		<document><![CDATA[Johnson waits to face MPs after Gray report into No 10 parties delayed #URL#]]></document>
		<document><![CDATA[Voices: If Boris Johnson’s successor called an election now – they wouldn’t win #URL#]]></document>
		<document><![CDATA[Arsenal ‘considering Douglas Luiz transfer swoop from Aston Villa’ after missing out on Newcastle-bound Bruno Guimaraes #URL#]]></document>
		<document><![CDATA[(LEAD) Lee, Yoon agree to hold one-on-one debate Jan. 31: parties #URL#]]></document>
		<document><![CDATA[Kate Middleton and Prince William ‘being careful’ about Prince George’s hobby, dad admits #URL#]]></document>
		<document><![CDATA[One prop bet we love for each team in the conference championships #URL#]]></document>
		<document><![CDATA[ET Online Budget Survey: What people see as the top risk to economic recovery &amp; why that matters #URL#]]></document>
		<document><![CDATA[‘Get a grip’: Joanna Lumley claims everyone’s on ‘the mental illness bandwagon’ #URL#]]></document>
		<document><![CDATA[Keene State swim team turns to Paige Carey #URL#]]></document>
		<document><![CDATA[Drew Barrymore surprises fans with ‘open relationship’ revelation about Luke Wilson #URL#]]></document>
		<document><![CDATA[Teen Mom’s Mackenzie McKee claims she was ‘BANNED’ from TikTok for ‘no reason’ in new video #URL#]]></document>
		<document><![CDATA[Retired cop, 65, found stabbed to death at home as woman, 54, and man, 21, arrested for murder #URL#]]></document>
		<document><![CDATA[Climate change threatens future Winter Olympics and snow sports, research claims #URL#]]></document>
		<document><![CDATA[How and why are indigenous people are on the front line of the climate crisis? #URL#]]></document>
		<document><![CDATA[‘I stand with Neil Young’: Joni Mitchell tells Spotify to remove her music over ‘lies that are costing people their lives’ #URL#]]></document>
		<document><![CDATA[Statue toppled in Puerto Rico before Spanish king’s visit #URL#]]></document>
		<document><![CDATA[Who is Scott Merryman? Kansas Man Wants to ‘Chop Off Joe Biden’s Head’ on ‘God’s Order’ #URL#]]></document>
		<document><![CDATA[White Man Arrested, Accused of Purposely Ramming Stolen SUV Into Interracial Couple’s Minnesota Home #URL#]]></document>
		<document><![CDATA[Teen Mom’s Leah Messer Introduces New Boyfriend to Her Kids Amid “Surprise” Romance #URL#]]></document>
		<document><![CDATA[Eerie pic of demon-like ‘ghost’ lurking outside Civil War army hospital leaves Reddit users on the fence #URL#]]></document>
		<document><![CDATA[Fifa president: more World Cups could save African migrants from death in the sea #URL#]]></document>
		<document><![CDATA[Teen Mom’s Kailyn Lowry Is Tired of Being Asked This Javi Marroquin Question #URL#]]></document>
		<document><![CDATA[‘Long Overdue’: Peabody, Sudbury Plow Drivers Preparing For Saturday’s Massive Nor’easter #URL#]]></document>
		<document><![CDATA[Teen Mom’s pregnant Catelynn Lowell reveals she’s having ‘uncomfortable’ contractions and says baby is ‘draining’ her #URL#]]></document>
		<document><![CDATA[Teen Mom’s Kailyn Lowry Says She and Her Kids Tested Positive for Coronavirus #URL#]]></document>
		<document><![CDATA[(3rd LD) Samsung SDI Q4 net up 14.6 pct on firm EV battery sales #URL#]]></document>
		<document><![CDATA[Not much upstairs and a right mess downstairs (not Katie Price, her house) #URL#]]></document>
		<document><![CDATA[Summary of domestic news in North Korea this week #URL#]]></document>
	</documents>
</author>