<author lang="en">
	<documents>
		<document><![CDATA[I bet he told the cops to bite him! #HASHTAG# #HASHTAG# #URL#]]></document>
		<document><![CDATA[The US: the only country were every school is a free shooting range and every student is a practice target. #HASHTAG# #URL#]]></document>
		<document><![CDATA[I really don't think 1,4 million #HASHTAG# is a record for #HASHTAG#. I recall some peak years in 1939-1945. #HASHTAG# #URL#]]></document>
		<document><![CDATA[#HASHTAG# #HASHTAG# threaten with suicide actions. I would say problem solved! #HASHTAG# #HASHTAG# #URL#]]></document>
		<document><![CDATA[If you watch The Passion of the Christ backwards, it's about a tortured zombie reconciling with his father.]]></document>
		<document><![CDATA[This is why a #HASHTAG# shouldn't wanna be a #HASHTAG#: #URL# #HASHTAG#]]></document>
		<document><![CDATA[I guess the proposal is to limit the amount of guns to two and the amount of bullets to 200. #HASHTAG# #HASHTAG# #HASHTAG# #URL#]]></document>
		<document><![CDATA[It is always the same in the Catholic church: standing in line to pay them. #HASHTAG# #HASHTAG# #HASHTAG# #URL#]]></document>
		<document><![CDATA[This is #HASHTAG# by itself: #URL#  #HASHTAG#e #HASHTAG#-rex #HASHTAG#.]]></document>
		<document><![CDATA[#HASHTAG# would be a great #HASHTAG#: I never used, oh I used; I had #HASHTAG# so I would not harm my body again, cancer made me use...etc]]></document>
		<document><![CDATA[If there are winter bugs there must be summer bugs! And I have found one. #HASHTAG#  
#URL# #URL#]]></document>
		<document><![CDATA[#USER# uni isn't that difficult. #HASHTAG#]]></document>
		<document><![CDATA[I guess this horse though it was a #HASHTAG#. #HASHTAG# #URL#]]></document>
		<document><![CDATA[#HASHTAG#: Attempting to #HASHTAG# when you really need to #HASHTAG# is ALWAYS a bad decision. #HASHTAG#]]></document>
		<document><![CDATA[One of comments of one of the #HASHTAG# on #HASHTAG# was: "damn it hot having clothes on for the first time" #HASHTAG# #URL#]]></document>
		<document><![CDATA[#HASHTAG# activist to end #HASHTAG#: He reached his desired weight of 35 kg and a seize 32. #HASHTAG# #URL#]]></document>
		<document><![CDATA[#HASHTAG# #HASHTAG# loses 11%. pitty we cannot like that! #HASHTAG#]]></document>
		<document><![CDATA[#USER# no you did not lie about the wheels ;) #URL#]]></document>
		<document><![CDATA[He needs a permanent change of address to State prison. #HASHTAG# #HASHTAG# #HASHTAG# #HASHTAG# #URL#]]></document>
		<document><![CDATA[I love the way how people believe in nonexistent things like: ghosts, God, honest politicians and solidarity. #HASHTAG# #URL#]]></document>
		<document><![CDATA[#HASHTAG# kills the game. #HASHTAG# #URL#]]></document>
		<document><![CDATA[Seriously 3 fire engines for a stupid squirrel? What happend to saving money, the economic crisis and Oh common sence? #URL#]]></document>
		<document><![CDATA[This child will have to attend to not one, not two, but three mother's days...poor baby. #HASHTAG# #HASHTAG# #HASHTAG# #URL#]]></document>
		<document><![CDATA[Fame and credits to the parents who named him Gaylord Silly, they must have been stoned. #HASHTAG# #HASHTAG# #URL#]]></document>
		<document><![CDATA[#USER# he only got the #HASHTAG#-sized panties and not the #HASHTAG# ones this poor basterd got. #HASHTAG# #URL#]]></document>
		<document><![CDATA[I am confident a lot will #HASHTAG# and much #HASHTAG# will be made in #HASHTAG# with the #HASHTAG# - #HASHTAG# switch]]></document>
		<document><![CDATA[ow yes...300 followers...totally NOT excited. #HASHTAG#]]></document>
		<document><![CDATA[I want his #HASHTAG#. #HASHTAG# #HASHTAG# #URL#]]></document>
		<document><![CDATA[It will be a very happy Europe day today!! #HASHTAG# #HASHTAG#e #HASHTAG# #HASHTAG# #HASHTAG# #HASHTAG# #HASHTAG#]]></document>
		<document><![CDATA[House arrest an effective punishment for young and old. #HASHTAG# #HASHTAG# #URL#]]></document>
		<document><![CDATA[#HASHTAG#: The first two black holes have been discovered on earth. #HASHTAG# #HASHTAG# #URL#]]></document>
		<document><![CDATA[#USER# you were bored ;)]]></document>
		<document><![CDATA[These two countries have a real borderline(r) relationship. #HASHTAG# #HASHTAG# #HASHTAG# #URL#]]></document>
		<document><![CDATA[I guess this only works when one is really hungry. #HASHTAG# #HASHTAG# #HASHTAG# #URL#]]></document>
		<document><![CDATA[Inspired by Mr #HASHTAG# I'm considering #HASHTAG# like: heidi the opossum (#URL#) or Phyllophaga (#URL#). #HASHTAG#]]></document>
		<document><![CDATA[My solution: use ancient #HASHTAG# wisdom and compel her to wear a #HASHTAG#. #HASHTAG# #HASHTAG# #HASHTAG# #URL#]]></document>
		<document><![CDATA[#USER# Because they've got nothing to lose?]]></document>
		<document><![CDATA[#HASHTAG# class 101: why it is always smart to look down a #HASHTAG#. #HASHTAG# #URL#]]></document>
		<document><![CDATA[#HASHTAG#: Woke, got up, breakfast, toilet, cycled for a while, dressed...damn wrong order. #URL#]]></document>
		<document><![CDATA[Why don't people learn...never go to #HASHTAG#. #HASHTAG# #HASHTAG# #HASHTAG# #HASHTAG# #URL#]]></document>
		<document><![CDATA[This is the real #HASHTAG#. #HASHTAG# #URL#]]></document>
		<document><![CDATA[Lol #USER#. I love this kind of articles! #URL#]]></document>
		<document><![CDATA[Owner states that his meals are very hot, even frozen! #HASHTAG# #HASHTAG# #HASHTAG# #URL#]]></document>
		<document><![CDATA[Once more #HASHTAG# regained it's neutral status, even boars know this by now. #HASHTAG# #HASHTAG# #URL#]]></document>
		<document><![CDATA[I thought #HASHTAG# builded a #HASHTAG# to keep #HASHTAG# out. Now I start to wonder they build walls keep #HASHTAG# in! #URL#]]></document>
		<document><![CDATA[A case of bad self judgement. But I love his willpower! #HASHTAG# #URL#…]]></document>
		<document><![CDATA[Dating a single mother. --- It's like continuing from someone else's saved game. #HASHTAG#]]></document>
		<document><![CDATA[According to #HASHTAG# this #HASHTAG# is very similar to his work at the #HASHTAG#: "everyone feels raped by the IMF" he said. #URL#]]></document>
		<document><![CDATA[My #HASHTAG# says it is time for my heart and mind to come together. Hope not because this would mean I would be in a car crash. #HASHTAG#]]></document>
		<document><![CDATA[This man is a real electric eal! #HASHTAG# #URL#]]></document>
		<document><![CDATA[A truly #HASHTAG# experience. Gotta love those #HASHTAG#. #HASHTAG# #URL#]]></document>
		<document><![CDATA[Left out of the article: "After he died the #HASHTAG# promptly ate him". #HASHTAG# #HASHTAG# #HASHTAG# #URL#]]></document>
		<document><![CDATA[Lil' Poopy running up the charts...not down your leg. #HASHTAG# #HASHTAG# #HASHTAG# #URL#]]></document>
		<document><![CDATA[Business ethics: Never change a profitable activity, #HASHTAG#. #HASHTAG# #HASHTAG# #HASHTAG# #HASHTAG# #URL#]]></document>
		<document><![CDATA[#HASHTAG#...mine says always goodbye. #HASHTAG#]]></document>
		<document><![CDATA[Ah that explains: hobo's don't smell! They just use this perfume! #HASHTAG# #HASHTAG# #HASHTAG# #URL#]]></document>
		<document><![CDATA[#HASHTAG# says #HASHTAG# won't change a thing. Thats true if you #HASHTAG# in two months like most #HASHTAG#. #HASHTAG# #URL#]]></document>
		<document><![CDATA[Fast food restaurant reported #HASHTAG# missing. I think it was an inside job! #HASHTAG# #URL#]]></document>
		<document><![CDATA[That explains why fat people are having intercourse. #HASHTAG##HASHTAG# #HASHTAG# #HASHTAG# #URL#]]></document>
		<document><![CDATA[It's located between Oliver's Mini Grocery and Leo's Open Lounge. #HASHTAG# #HASHTAG# #HASHTAG# #HASHTAG# #URL#]]></document>
		<document><![CDATA[I totally agree with #HASHTAG# and #HASHTAG#: There is absolutely no need to intervene in #HASHTAG#. #HASHTAG# #HASHTAG#  #URL#]]></document>
		<document><![CDATA[Since long I haven't heard off #HASHTAG# violence in #HASHTAG#. So all must be well then! #HASHTAG# #HASHTAG# #HASHTAG#]]></document>
		<document><![CDATA[17% of the candidates calculated the chance of having statistics exam  &gt;5%. Now, all expect the chance on terrible grades 110%. #HASHTAG#]]></document>
		<document><![CDATA[This classifies the #HASHTAG# as a minority. So please act like a one and be so kind to shut up! (2/2) #HASHTAG# #HASHTAG# #URL#]]></document>
		<document><![CDATA[I think he just likes apple pits a lot. #HASHTAG# #HASHTAG# #URL#]]></document>
		<document><![CDATA[I bet there were some #HASHTAG# women #HASHTAG# but for the sake of not calling them fat, they asked men to get off. #URL#]]></document>
		<document><![CDATA[Attention #HASHTAG# section! Looking for my #HASHTAG#....again.]]></document>
		<document><![CDATA[And the effect is: even less news is posted. Good call. #HASHTAG# #HASHTAG# #HASHTAG#
#URL#]]></document>
		<document><![CDATA[Am I the only one who thinks about a dirty #HASHTAG# porn when he hears the title #HASHTAG# III? Please answer! #HASHTAG# #HASHTAG#]]></document>
		<document><![CDATA[I want to be an organ donor as well. This is my first organ I'm about to donate. #HASHTAG# #HASHTAG# #USER# #URL#]]></document>
		<document><![CDATA[A #HASHTAG#: so he probably sends them bill for 4 hours of wage supplemented with taxes and office expenses. #HASHTAG# #URL#]]></document>
		<document><![CDATA[I expect #HASHTAG# to announce his goal to top the worlds #HASHTAG# list. Only 77940000 people to go. #HASHTAG# #HASHTAG# #URL#]]></document>
		<document><![CDATA[Well at least there is no decline in the #HASHTAG# church: #URL# #HASHTAG# #HASHTAG# #HASHTAG# #HASHTAG# #HASHTAG#]]></document>
		<document><![CDATA[#HASHTAG#. The only thing I need to know about the #HASHTAG# is that I'm in the centre of it. #HASHTAG#

#URL#]]></document>
		<document><![CDATA[Yeah Yeah how did he wound up in this situation....#HASHTAG# #URL#]]></document>
		<document><![CDATA[In #HASHTAG# on average one rape takes place every twenty minutes! This must be a record! #HASHTAG# #HASHTAG# #URL#]]></document>
		<document><![CDATA[And the #HASHTAG# said to her: "get up and walk, thou shall never be #HASHTAG# again". #HASHTAG# #URL#]]></document>
		<document><![CDATA[The true meaning of #HASHTAG#: some citizens are more equal then others! #HASHTAG# #HASHTAG# #HASHTAG# #HASHTAG# #URL#]]></document>
		<document><![CDATA[#USER# Napoleon Dynamite...Great movie!]]></document>
		<document><![CDATA[And only the #HASHTAG# are bad....uhuhummm...:S. #URL# #HASHTAG# #HASHTAG#]]></document>
		<document><![CDATA[Ow yea I will start sending my #HASHTAG# socks, so they can smell my age for approval. #HASHTAG# #HASHTAG# #URL#]]></document>
		<document><![CDATA[Getting up at 05:20 is always such fun. #HASHTAG# #HASHTAG#]]></document>
		<document><![CDATA[I wonder what the advice would be when teens become suicidal due to bullying...here is a gun/rope? #HASHTAG# #URL#]]></document>
		<document><![CDATA[During #HASHTAG# someone says to a dude kissing a girl: "That isn't your wife!" The dude's response: "I know but she tastes good". #HASHTAG#]]></document>
		<document><![CDATA[For the eight year in a row, the #HASHTAG# haven't reached the finals of the #HASHTAG#. That's some talent to! #HASHTAG#]]></document>
		<document><![CDATA[As expected #HASHTAG# proposes a democratic solotion. He wants a peace conference with those who agree with him. #HASHTAG# #URL#]]></document>
		<document><![CDATA[Firework victims is just a modern way of natural selection based upon stupidity. #HASHTAG# #HASHTAG# #HASHTAG# #URL#]]></document>
		<document><![CDATA[Historic discovery: the lift which #HASHTAG# used to hide massive ammounts of #HASHTAG#, has been found! #HASHTAG# #URL#]]></document>
		<document><![CDATA[This is the only pleasant manner in which #HASHTAG# can happen. #URL# #HASHTAG# #HASHTAG# #HASHTAG#]]></document>
		<document><![CDATA[So confusing it made my head hurt: a highly aged #HASHTAG# bearing testimony of a future World War. #HASHTAG# #URL#]]></document>
		<document><![CDATA[2012 was UK's second wettest year. Mrs Dalmans' (46) ten years dry patch was finally over. #HASHTAG# #HASHTAG# #HASHTAG# #HASHTAG#]]></document>
		<document><![CDATA[Well there is something which is never going to happen. Look which PM is #HASHTAG# his hand. #HASHTAG# #HASHTAG# #URL#]]></document>
		<document><![CDATA[I will never become polygamous because of the severe punishment: multiple mothers in law. #HASHTAG#]]></document>
		<document><![CDATA[Ah Simpson's mortuary that explains! Its spokesman was probably quoted as saying, "D'oh." #HASHTAG# #HASHTAG# #URL#]]></document>
		<document><![CDATA[And once more honesty is the best policy, but insanity proves to be the best defense. #HASHTAG# #HASHTAG# #HASHTAG# #URL#]]></document>
		<document><![CDATA[My #HASHTAG# is so large I use #HASHTAG# having #HASHTAG#-signs. #HASHTAG#]]></document>
		<document><![CDATA[I love it when there is a #HASHTAG# in one of my jeans while I'm doing #HASHTAG#. #HASHTAG#]]></document>
		<document><![CDATA[Amazing how much motivation some people have to obtain porn. #HASHTAG# #HASHTAG# #HASHTAG# #URL#]]></document>
		<document><![CDATA[In 1000 years #HASHTAG# will go #HASHTAG#. Our greatest losses will be: sushi, nuclear disasters, useless gadgets &amp; funny tv-shows. #HASHTAG#]]></document>
		<document><![CDATA[Ow yes I clearly see how a nuclear strike can be preemtive/preventive. #HASHTAG# #HASHTAG# #HASHTAG# #HASHTAG# #URL#]]></document>
		<document><![CDATA[No pain no gain is nonsense! Once I faceplanted myself. It resulted in a lot of pain and medical bills, thus no gain. #HASHTAG# #HASHTAG#]]></document>
		<document><![CDATA[The #HASHTAG# is trying to intervene in #HASHTAG#. Now I'm reassured #HASHTAG# can stay in office until he is 80. Keep up the good work! #HASHTAG#]]></document>
		<document><![CDATA[#HASHTAG# #HASHTAG# ban #HASHTAG# #HASHTAG#....Welcome to the #HASHTAG# and #HASHTAG#. #HASHTAG# #HASHTAG#e #HASHTAG# #HASHTAG#]]></document>
		<document><![CDATA[Truthful confessions aren't important, closing as much cases as possible is! #HASHTAG# #HASHTAG# #HASHTAG# #URL#]]></document>
		<document><![CDATA[Going once for the money, going twice for the show...sold to the man wearing blue suede shoes. #HASHTAG# #HASHTAG# #HASHTAG# #URL#]]></document>
		<document><![CDATA[And that's why we invented those bumper stickers saying: "baby on board". #HASHTAG# #HASHTAG# #HASHTAG# #URL#]]></document>
		<document><![CDATA[If you watch House M.D. backwards, it's still never Lupus. #HASHTAG#]]></document>
		<document><![CDATA[A perfect example of useful...NOT: #URL# #HASHTAG#]]></document>
		<document><![CDATA[Happy Darwin day! Damn, #HASHTAG# are really #HASHTAG#! #HASHTAG# #HASHTAG# #URL#]]></document>
		<document><![CDATA[#HASHTAG# reports #HASHTAG# radiation levels are low. Do they mean the Hiroshima and Nagasaki levels? #HASHTAG#]]></document>
		<document><![CDATA[(2/2) Retired sea dogs...this is how they actually look like. #HASHTAG# #URL#]]></document>
		<document><![CDATA[One of the mightiest man on earth, flying his own plane cannot circumvent aviation laws, 1-0 for bureaucracy! #HASHTAG# #URL#]]></document>
		<document><![CDATA[Dear #HASHTAG#: since when is lying a personal reason. #URL# #HASHTAG# #HASHTAG#]]></document>
		<document><![CDATA[If I ever won 10000000 dollar, I would give it away to charity. #HASHTAG#]]></document>
		<document><![CDATA[#HASHTAG#: #HASHTAG# peace negotiator Arsala Rahmani shot dead. Is it now possible for him to rest in #HASHTAG#? #HASHTAG# #HASHTAG#]]></document>
		<document><![CDATA[I'm 1,72m x 0.25m x 0.6m. A #HASHTAG# is 0.4m x 0.15m x 0.3m. Thus a #HASHTAG# needs to be 2.12m x 0.4m x 0.9m to #HASHTAG#. #HASHTAG#]]></document>
		<document><![CDATA[Yes! Now #HASHTAG# will get a swift trail and rapidly receive his deserved #HASHTAG#. #HASHTAG# #HASHTAG#e #HASHTAG# #HASHTAG#]]></document>
		<document><![CDATA[He is homeless and he has no bag thus where else should he store his belongings? #HASHTAG# #HASHTAG# #URL#]]></document>
		<document><![CDATA[#HASHTAG# now? How long before we move onto #HASHTAG#? At least they'll come already #HASHTAG#. #HASHTAG# #HASHTAG# #HASHTAG# #URL#]]></document>
		<document><![CDATA[Bringing back #HASHTAG# in a #HASHTAG# can be good. So from now, the second time I wear a #HASHTAG# I will wear it inside-out. #HASHTAG#]]></document>
		<document><![CDATA[Too much deaths due to road accidents. What is the problem there are too much Chinese anyway! #HASHTAG# #HASHTAG# #HASHTAG# #URL#]]></document>
		<document><![CDATA[Yay new #HASHTAG# in #HASHTAG#. This will give them a clean start! #HASHTAG#]]></document>
		<document><![CDATA[Have been waiting so long for my #HASHTAG#...I've been thinking about buying #HASHTAG#. #HASHTAG# #HASHTAG#]]></document>
		<document><![CDATA[Can't get them to eat #HASHTAG#, but #HASHTAG# they just love! At least he is very attractive now. #HASHTAG# #URL#]]></document>
		<document><![CDATA[Q: What did the doctor say to the midget? A: You'll just have to be a little patient! #HASHTAG#]]></document>
		<document><![CDATA[#USER# of de wasmachine op centrifugeren]]></document>
		<document><![CDATA[I truly believe there are things which should not be #HASHTAG#. #HASHTAG#]]></document>
		<document><![CDATA[How can ANYONE prefer #HASHTAG# to #HASHTAG#? One is for children, and the other is for adults. #HASHTAG# #URL#]]></document>
		<document><![CDATA[Not for even a second she thinks she could be the problem...I like this woman #HASHTAG# #HASHTAG# #URL#]]></document>
		<document><![CDATA[#HASHTAG# getting lost is no fun anymore. Damn you google maps! #HASHTAG# #HASHTAG#]]></document>
		<document><![CDATA[Dear #HASHTAG# enthusiasts since the Mayans failed I provide you with some new dates to get eager about. Yay! #URL#]]></document>
		<document><![CDATA[#USER# now I  feel sorry for you. Oh no wait...#HASHTAG# ;)]]></document>
		<document><![CDATA[Ow yeah this is what I would call doggy style. #HASHTAG# #HASHTAG# #HASHTAG# #URL#]]></document>
		<document><![CDATA[And there the cute little piggy meets its future. #HASHTAG# #URL#]]></document>
		<document><![CDATA[Why is it that people become #HASHTAG# when the see a #HASHTAG#. #HASHTAG#]]></document>
		<document><![CDATA[The only thing milkshakes give me is a brain freeze and that's like the opposite of a brain boost. #HASHTAG# #HASHTAG# #URL#]]></document>
		<document><![CDATA[Even when tell sell still published its ads in newspapers they weren't any better. #HASHTAG# #URL#]]></document>
		<document><![CDATA[She must have been a few sandwiches short of a picnic to go with this plan. #HASHTAG# #URL#]]></document>
		<document><![CDATA[How to make your job go south for four #HASHTAG#. #HASHTAG# #URL#]]></document>
		<document><![CDATA[Teens drugging their parents for some.internet acces. I say handled it like a boss. #HASHTAG# #HASHTAG# #URL#]]></document>
		<document><![CDATA[People fighting over a flag...why don't they play #HASHTAG#? #HASHTAG# #HASHTAG# #HASHTAG#
#URL#]]></document>
		<document><![CDATA[Why does one steal 400 #HASHTAG#..where to leave them? Women can only (simultaneously) use two and man only one. #HASHTAG# #URL#]]></document>
		<document><![CDATA[#USER# no I wouls not risk a frienship for a relationship. #HASHTAG#]]></document>
		<document><![CDATA[#USER# start reading my 88 tweets :P]]></document>
		<document><![CDATA[#USER# Daily Catharsis is out! #URL#… ▸ Top stories today via #USER# #USER# #USER# // thanks!]]></document>
		<document><![CDATA[Not only #HASHTAG# prisoners were tortured with his songs....the whole world was. #HASHTAG# #HASHTAG# #URL#]]></document>
		<document><![CDATA[#HASHTAG# #HASHTAG# scandal...it at least explains all the theater and the useless #HASHTAG#. #HASHTAG# #HASHTAG#]]></document>
		<document><![CDATA[#USER# use a hammer... *splat*.... success guaranteed! #HASHTAG#]]></document>
		<document><![CDATA[Nice #HASHTAG# quote: I love to be your maid of honour and I want you to know I will do it again when this marriage craps out. #HASHTAG#]]></document>
		<document><![CDATA[Die van Dooyenburghe Allgemeine is out! #URL# ▸ Top stories today via #USER# #USER# #USER# // thanks]]></document>
		<document><![CDATA[That is why it is called a waterfall...not only water falls! #HASHTAG# #HASHTAG# #HASHTAG# #URL#]]></document>
		<document><![CDATA[#HASHTAG# bumper planes test does not provide the expected success. #HASHTAG# #HASHTAG# #HASHTAG# #URL#]]></document>
		<document><![CDATA[Please #HASHTAG#: how can constantly increasing your #HASHTAG# be a good thing?? #HASHTAG# #URL#]]></document>
		<document><![CDATA[#HASHTAG# are like #HASHTAG#...if they don't get #HASHTAG# they'll start to yell. #HASHTAG#]]></document>
		<document><![CDATA[So #HASHTAG# on your wrist aren't bad at all. #HASHTAG# #HASHTAG# #URL#]]></document>
		<document><![CDATA[50 years to prison it is for #HASHTAG#. Well there is a nice way to avoid your #HASHTAG#. #HASHTAG#]]></document>
		<document><![CDATA[Guide: there are only two of these eagles left, we are breding them..Munch munch munch.. Eh now there is only one left. #URL#]]></document>
		<document><![CDATA[Well it's better than sitting, getting bored and being laughed at by people visiting the zoo. #HASHTAG# #HASHTAG# #HASHTAG# #URL#]]></document>
		<document><![CDATA[#USER# in the #HASHTAG# genre. #URL#]]></document>
		<document><![CDATA[Ow yeah a good cat-suit always does the trick. #HASHTAG# #HASHTAG# #HASHTAG# #HASHTAG# #URL#]]></document>
		<document><![CDATA[Isn't it just some kind of community centre because calling it a #HASHTAG# would be a contradictio interminis? #HASHTAG# #URL#]]></document>
		<document><![CDATA[Don't count your chickens(wings) before they are hatched/stolen. #HASHTAG# #HASHTAG# #URL#]]></document>
		<document><![CDATA[Must be a textbook which is used in Alabama or South Carolina. #HASHTAG# #HASHTAG# #URL#]]></document>
		<document><![CDATA[It is true you do lose weight...I lost 60kg...I divorced her! #HASHTAG# #HASHTAG# #HASHTAG# #URL#]]></document>
		<document><![CDATA[Nice way of fact checking #HASHTAG# // OR // a nice way to make a first impression upon new facebook friends. #HASHTAG#
#URL#]]></document>
		<document><![CDATA[Change the name, keep the policy and the #HASHTAG# is satisfied for some time. I love politics! #HASHTAG# #HASHTAG# #HASHTAG# #URL#]]></document>
		<document><![CDATA[Is #HASHTAG# the highest form of #HASHTAG#? Sure it is....;).]]></document>
		<document><![CDATA[My wife needed a kidney transplant 3 years ago and I was a perfect match. I still miss her occasionally. #HASHTAG# #URL#]]></document>
		<document><![CDATA[I find the term #HASHTAG# so useless. Isn't war always a crime? Except those started by the #HASHTAG# of course. #HASHTAG#]]></document>
		<document><![CDATA[My favourite parental lie: but you ARE beautiful my princess! Mostly so untrue that it sounds like #HASHTAG#. #URL#]]></document>
		<document><![CDATA[#USER# If I was a fish I would think that too ;)]]></document>
		<document><![CDATA[#USER# That is what normal people would call snoring ;)]]></document>
		<document><![CDATA[This guy made me believe the stupidity gene excists. #HASHTAG# #HASHTAG# #HASHTAG# #HASHTAG# #HASHTAG# #HASHTAG# #URL#]]></document>
		<document><![CDATA[And they thought reviewing a textbook, before finally publishing it, was a luxury. #HASHTAG# #HASHTAG# #URL#]]></document>
		<document><![CDATA[This school is afraid its boys will go to second base with her ;). #URL# #HASHTAG# #HASHTAG# #HASHTAG# #HASHTAG# #HASHTAG#]]></document>
		<document><![CDATA[I guess he asked where he could get a #HASHTAG#. #HASHTAG# #URL# #URL#]]></document>
		<document><![CDATA[Well I don't know, maybe not to shit on the floor! #HASHTAG# #URL#]]></document>
		<document><![CDATA[The #HASHTAG# has 315.1 million inhabitants of which 4.3 million are #HASHTAG# members. This means the NRA represents 1.4% of the population (1/2)]]></document>
		<document><![CDATA[yes, sure I always weigh the things I'm saying. #HASHTAG#]]></document>
		<document><![CDATA[#HASHTAG# giving away het clothes...This is NOT a #HASHTAG# but a #HASHTAG#. #HASHTAG# #URL# #URL#]]></document>
		<document><![CDATA[Where did her life go wrong?? #URL# #HASHTAG# #HASHTAG#e #HASHTAG# #HASHTAG#]]></document>
		<document><![CDATA[Lol Lenin who says keep talking...the #HASHTAG#. #HASHTAG# #HASHTAG# #HASHTAG# #URL#]]></document>
		<document><![CDATA[This #HASHTAG# will make a great #HASHTAG# someday, already has experience handing out other people's #HASHTAG#. #HASHTAG# #URL#]]></document>
		<document><![CDATA[That was the easy part...the hard part will be getting up. #HASHTAG# #URL#]]></document>
		<document><![CDATA[While taking them to their parents, the Asians succeeded to take the romance out of hookers. :( #HASHTAG# #URL#]]></document>
		<document><![CDATA[#HASHTAG# of the #HASHTAG# most likely died of a severe case of the #HASHTAG#. #HASHTAG#]]></document>
		<document><![CDATA[Q: What's the Internet's favorite animal? A: The lynx. #HASHTAG#]]></document>
		<document><![CDATA[At least there is some truth in those fisherman's tales. Luckily it will make some nice sushi. #HASHTAG# #URL#]]></document>
		<document><![CDATA[If you watch Human Centipede backwards, it is a compelling story about a caring german doctor attempting to separate 3 conjoined triplets.]]></document>
		<document><![CDATA[Radio just mentioned a wrong-way driver has been seen. A!? I see hundreds of them! #HASHTAG# #HASHTAG#]]></document>
		<document><![CDATA[This article raises just one question.......WHY?! #HASHTAG# #URL#]]></document>
		<document><![CDATA[And again proof that fat people are happier. #HASHTAG# #URL#]]></document>
		<document><![CDATA[I bet the tuna looked something like this. #HASHTAG# #HASHTAG# #HASHTAG# #HASHTAG# #URL# #URL#]]></document>
		<document><![CDATA[LOL: I wonder what this says about the quality of female athletes in #HASHTAG#. #HASHTAG# #HASHTAG# #HASHTAG# #URL#]]></document>
		<document><![CDATA[I handle my #HASHTAG# like #HASHTAG# handles #HASHTAG#. I just build a gigantic #HASHTAG# around them and all will be fine. #HASHTAG# #HASHTAG#e]]></document>
		<document><![CDATA[#USER# thanks :)]]></document>
		<document><![CDATA[#HASHTAG#: #HASHTAG# #HASHTAG#. It are always the #HASHTAG# betraying you. Paul you should have known better. #HASHTAG# #URL#]]></document>
		<document><![CDATA[#HASHTAG# I'm impressed: never met such a small mind in such a big head before. #HASHTAG# #HASHTAG# #HASHTAG#]]></document>
		<document><![CDATA[#HASHTAG#, staying alive: epic fail. #HASHTAG#]]></document>
		<document><![CDATA[Guess there was no nice inheritance to stay alive for. #HASHTAG# #HASHTAG# #URL#]]></document>
	</documents>
</author>